{
    "default": {
        "name": "",
        "owner_id": 0,
        "quality": 5,
        "maxQuality": 20,
        "species": "",
        "buildings": [],
        "garrison": [],
        "siegeCamp": []
    },
    "1": {
        "name": "NewHaven",
        "owner_id": 107886996365508608,
        "quality": 0,
        "maxQuality": 20,
        "species": "duck",
        "buildings": [
            "castle"
        ],
        "garrison": [
            {
                "troop_name": "Duck Militia",
                "amount": 15,
                "user_id": 107886996365508608
            },
            {
                "troop_name": "Duck Guard",
                "amount": 57,
                "user_id": 107886996365508608
            }
        ],
        "siegeCamp": []
    },
    "2": {
        "name": "Climate Change",
        "owner_id": 479504133993529344,
        "quality": 0,
        "maxQuality": 20,
        "species": "duck",
        "buildings": [],
        "garrison": [],
        "siegeCamp": []
    },
    "3": {
        "name": "Peoples Republic of Antarctica",
        "owner_id": 692095041635614750,
        "quality": 0,
        "maxQuality": 20,
        "species": "penguin",
        "buildings": [],
        "garrison": [],
        "siegeCamp": []
    }
}