{
    "default": {
        "quacks": 1,
        "quackStreak": 1,
        "quackedToday": false,
        "quackRank": "",
        "spentQuacks": 0,
        "quackerinos": 0,
        "safety_count": 5,
        "renown": 0,
        "support": 0,
        "supportee_id": 0,
        "liege_id": 0,
        "ally_ids": [],
        "taxPerVassalLand": 0,
        "homeland_id": -1,
        "land_ids": [],
        "mischief": false,
        "species": "",
        "vassal_waitlist_ids": [],
        "spins": 0,
        "daily_reminder": false
    }
}